DraftUtils-stubs/__init__.pyi
Drawing-stubs/__init__.pyi
DrawingGui-stubs/__init__.pyi
Fem-stubs/__init__.pyi
FemGui-stubs/__init__.pyi
FreeCAD-stubs/Base.pyi
FreeCAD-stubs/_Console.pyi
FreeCAD-stubs/_Qt.pyi
FreeCAD-stubs/_Units.pyi
FreeCAD-stubs/__init__.pyi
FreeCADDbg-stubs/__init__.pyi
FreeCADGui-stubs/_PySideUic.pyi
FreeCADGui-stubs/_Selection.pyi
FreeCADGui-stubs/_TaskDialogPython.pyi
FreeCADGui-stubs/__init__.pyi
FreeCADTemplates/__init__.py
FreeCADTemplates/py.typed
FreeCADTemplates/qt_types.py
FreeCADTemplates/qt_types.pyi
FreeCADTemplates/templates.py
FreeCADTemplates/type_consts.py
Import-stubs/__init__.pyi
ImportGui-stubs/__init__.pyi
JtReader-stubs/__init__.pyi
Material-stubs/__init__.pyi
Materials-stubs/__init__.pyi
Measure-stubs/__init__.pyi
Mesh-stubs/__init__.pyi
MeshGui-stubs/__init__.pyi
MeshPart-stubs/__init__.pyi
Part-stubs/BRepFeat.pyi
Part-stubs/ChFi2d.pyi
Part-stubs/Geom2d.pyi
Part-stubs/GeomPlate.pyi
Part-stubs/ShapeFix.pyi
Part-stubs/ShapeUpgrade.pyi
Part-stubs/__init__.pyi
PartDesign-stubs/__init__.pyi
PartDesignGui-stubs/__init__.pyi
Path-stubs/Voronoi.pyi
Path-stubs/__init__.pyi
PathApp-stubs/__init__.pyi
PathGui-stubs/__init__.pyi
Points-stubs/__init__.pyi
ReverseEngineering-stubs/__init__.pyi
Robot-stubs/__init__.pyi
Sandbox-stubs/__init__.pyi
SandboxGui-stubs/__init__.pyi
ShapeFix-stubs/__init__.pyi
Sketcher-stubs/__init__.pyi
SketcherGui-stubs/__init__.pyi
Spreadsheet-stubs/__init__.pyi
SpreadsheetGui-stubs/__init__.pyi
Surface-stubs/__init__.pyi
TechDraw-stubs/__init__.pyi
TechDrawGui-stubs/__init__.pyi
Web-stubs/__init__.pyi
WebGui-stubs/__init__.pyi
_PartDesign-stubs/__init__.pyi
freecad_stubs-1.0.17.dist-info/LICENSE
freecad_stubs-1.0.17.dist-info/METADATA
freecad_stubs-1.0.17.dist-info/WHEEL
freecad_stubs-1.0.17.dist-info/top_level.txt
freecad_stubs-1.0.17.dist-info/RECORD
