Metadata-Version: 2.1
Name: freecad-stubs
Version: 1.0.17
Summary: Python stubs for FreeCAD
Author: ostr00000
License: GPL-3.0
Project-URL: repository, https://github.com/ostr00000/freecad-stubs
Keywords: FreeCAD,stubs
Classifier: Development Status :: 5 - Production/Stable
Classifier: Intended Audience :: Developers
Classifier: License :: OSI Approved :: GNU General Public License v3 (GPLv3)
Classifier: Operating System :: OS Independent
Classifier: Programming Language :: Python :: 3.6
Classifier: Programming Language :: Python :: 3.7
Classifier: Programming Language :: Python :: 3.8
Classifier: Programming Language :: Python :: 3.9
Classifier: Programming Language :: Python :: 3.10
Classifier: Programming Language :: Python :: 3.11
Classifier: Programming Language :: Python :: 3.12
Classifier: Typing :: Stubs Only
Requires-Python: >=3.6
License-File: LICENSE
Requires-Dist: qtpy
Provides-Extra: all
Requires-Dist: freecad-stubs[check,generate] ; extra == 'all'
Provides-Extra: check
Requires-Dist: PyQt5 ; extra == 'check'
Requires-Dist: PyQt5-stubs ; extra == 'check'
Requires-Dist: black ; extra == 'check'
Requires-Dist: mypy ; extra == 'check'
Requires-Dist: pylint ; extra == 'check'
Requires-Dist: pyright ; extra == 'check'
Requires-Dist: pytest ; extra == 'check'
Requires-Dist: qtpy ; extra == 'check'
Provides-Extra: generate
Requires-Dist: more-itertools ; extra == 'generate'
Requires-Dist: pcpp ; extra == 'generate'
